yetl/__init__.py
yetl/__main__.py
yetl/cli/_init.py
yetl/cli/metadata_provider/__init__.py
yetl/cli/metadata_provider/_xlsx.py
yetl/config/__init__.py
yetl/config/_config.py
yetl/config/_decorators.py
yetl/config/_logging_config.py
yetl/config/_project.py
yetl/config/_spark_context.py
yetl/config/_stage_type.py
yetl/config/_table_mapping.py
yetl/config/_tables.py
yetl/config/_timeslice.py
yetl/config/_utils.py
yetl/config/deltalake.py
yetl/config/table/__init__.py
yetl/config/table/_deltalake.py
yetl/config/table/_factory.py
yetl/config/table/_read.py
yetl/config/table/_table.py
yetl/config/table/_table_type.py
yetl/config/table/_write.py
yetl/resource/__init__.py
yetl/resource/logging.yaml
yetl/resource/project.yaml
yetl/resource/sibytes_yetl_pipeline_schema.json
yetl/resource/sibytes_yetl_project_schema.json
yetl/resource/sibytes_yetl_tables_schema.json
yetl/resource/tables.xlsx
yetl/validation/__init__.py
yetl/validation/_validate.py
yetl/workflow/__init__.py
yetl/workflow/_dlt.py
yetl/workflow/_multi_threaded.py
yetl/workflow/_notebook.py
yetl_framework-3.0.0.dist-info/METADATA
yetl_framework-3.0.0.dist-info/WHEEL
yetl_framework-3.0.0.dist-info/top_level.txt
yetl_framework-3.0.0.dist-info/RECORD
