Metadata-Version: 2.1
Name: yetl-framework
Version: 3.0.0
Summary: yet (another spark) etl framework
Home-page: https://www.yetl.io/
Author: Shaun Ryan
Author-email: shaun_chiburi@hotmail.com
License: MIT
Project-URL: GitHub, https://github.com/sibytes/yetl
Project-URL: Documentation, https://www.yetl.io/
Classifier: License :: OSI Approved :: MIT License
Classifier: Programming Language :: Python :: 3
Classifier: Programming Language :: Python :: 3.8
Classifier: Programming Language :: Python :: 3.9
Classifier: Programming Language :: Python :: 3.10
Requires-Dist: PyYAML
Requires-Dist: jinja2
Requires-Dist: pydantic
Requires-Dist: jsonschema
Requires-Dist: typer
Requires-Dist: pandas
Requires-Dist: openpyxl
Requires-Dist: delta-spark
Requires-Dist: pyspark
